pyVSSSReferee/RefereeComm.py
pyVSSSReferee/__init__.py
pyVSSSReferee/protocols/__init__.py
pyVSSSReferee/protocols/vssref_command_pb2.py
pyVSSSReferee/protocols/vssref_common_pb2.py
pyVSSSReferee/protocols/vssref_placement_pb2.py
tests/__init__.py
tests/test_RefereeComm.py
pyVSSSReferee-2.0.0.dist-info/LICENSE
pyVSSSReferee-2.0.0.dist-info/METADATA
pyVSSSReferee-2.0.0.dist-info/WHEEL
pyVSSSReferee-2.0.0.dist-info/top_level.txt
pyVSSSReferee-2.0.0.dist-info/RECORD
